alu_ops/adder.sv
/*

One-bit full adder implementation in SystemVerilog.

Inputs:
    - a: 1-bit input for the first number
    - b: 1-bit input for the second number
    - cin: 1-bit input for the carry in
Outputs:
    - s: 1-bit output for the addition result
    - cout: 1-bit output for the carry out

*/

module adder(a, b, cin, s, cout);
    input logic a, b, cin;
    output logic s, cout;

    logic xorab;
    xor(xorab, a, b);

    xor(s, xorab, cin);
    
    logic and0, and1;
    and(and0, xorab, cin);
    and(and1, a, b);
    or(cout, and0, and1);
endmodule

testbench_sv/adder_testbench.sv
/*

Testbench code for the adder module

*/

module adder_testbench();
    logic a, b, cin, s, cout;

    adder dut(.a, .b, .cin, .s, .cout);

    initial begin
        $dumpfile("testbench_vcd/adder_testbench.vcd");
        $dumpvars(0, adder_testbench);
        a = 0; b = 0; cin = 0; #10;
        a = 0; b = 0; cin = 1; #10;
        a = 0; b = 1; cin = 0; #10;
        a = 0; b = 1; cin = 1; #10;
        a = 1; b = 0; cin = 0; #10;
        a = 1; b = 0; cin = 1; #10;
        a = 1; b = 1; cin = 0; #10;
        a = 1; b = 1; cin = 1; #10;
    end
endmodule

testbench_vcd/adder_testbench.vcd
$date
	Fri May 23 16:31:09 2025
$end
$version
	Icarus Verilog
$end
$timescale
	1s
$end
$scope module adder_testbench $end
$var wire 1 ! s $end
$var wire 1 " cout $end
$var reg 1 # a $end
$var reg 1 $ b $end
$var reg 1 % cin $end
$scope module dut $end
$var wire 1 # a $end
$var wire 1 & and0 $end
$var wire 1 ' and1 $end
$var wire 1 $ b $end
$var wire 1 % cin $end
$var wire 1 " cout $end
$var wire 1 ! s $end
$var wire 1 ( xorab $end
$upscope $end
$upscope $end
$enddefinitions $end
$comment Show the parameter values. $end
$dumpall
$end
#0
$dumpvars
0(
0'
0&
0%
0$
0#
0"
0!
$end
#10
1!
1%
#20
1(
0%
1$
#30
1"
0!
1&
1%
#40
0"
1!
0&
0%
0$
1#
#50
1"
0!
1&
1%
#60
0&
0(
1'
0%
1$
#70
1!
1%
