alu_ops/barrel_shifter.sv
/*

Barrel shifter implemenetation (no rotation).

Inputs:
    - in: 32-bit input for what needs to be shifted
    - how_many: 5-bit input for how many places to shift by
    - dir: 1-bit boolean specifying which direction to shift
        - 0 if left, 1 if right
    - arithmetic: 1-bit boolean specifying if using arithmetic or logical shift
        - 0 if logical, 1 if arithmetic
Outputs:
    - out: 32-bit result of the shifting operation

*/

module barrel_shifter(in, how_many, dir, arithmetic, out);
    input logic [31:0] in;
    input logic [4:0] how_many;
    input logic dir;
    input logic arithmetic;
    output logic [31:0] out;

    logic [31:0] s0, s1, s2, s3;
    always_comb begin
        if(dir) begin
            if(arithmetic) begin
                s0 = how_many[0] ? 32'(signed'(in[31:1])) : in;
                s1 = how_many[1] ? 32'(signed'(s0[31:2])) : s0;
                s2 = how_many[2] ? 32'(signed'(s1[31:4])) : s1;
                s3 = how_many[3] ? 32'(signed'(s2[31:8])) : s2;
                out = how_many[4] ? 32'(signed'(s3[31:16])) : s3;
            end else begin
                s0 = how_many[0] ? {1'b0, in[31:1]} : in;
                s1 = how_many[1] ? {2'b0, s0[31:2]} : s0;
                s2 = how_many[2] ? {4'b0, s1[31:4]} : s1;
                s3 = how_many[3] ? {8'b0, s2[31:8]} : s2;
                out = how_many[4] ? {16'b0, s3[31:16]} : s3;
            end
        end else begin
            s0 = how_many[0] ? {in[30:0], 1'b0} : in;
            s1 = how_many[1] ? {s0[29:0], 2'b0} : s0;
            s2 = how_many[2] ? {s1[27:0], 4'b0} : s1;
            s3 = how_many[3] ? {s2[23:0], 8'b0} : s2;
            out = how_many[4] ? {s3[15:0], 16'b0} : s3;
        end
    end
endmodule

testbench_sv/barrel_shifter_testbench.sv
/*

Testbench code for the barrel_shifter module

*/


module barrel_shifter_testbench();
    logic [31:0] in, out;
    logic dir, arithmetic;
    logic [4:0] how_many;

    barrel_shifter dut(.in, .how_many, .dir, .arithmetic, .out);

    initial begin
        $dumpfile("testbench_vcd/barrel_shifter_testbench.vcd");
        $dumpvars(0, barrel_shifter_testbench);
        for(integer i = 0; i < 33; i++) begin
            in = 32'b11111111111111111111111111111111; how_many = i; dir = 1'b0; arithmetic = 1'b0; #10;
        end
        for(integer i = 0; i < 33; i++) begin
            in = 32'b11111111111111111111111111111111; how_many = i; dir = 1'b1; arithmetic = 1'b0; #10;
            in = 32'b11111111111111111111111111111111; how_many = i; dir = 1'b1; arithmetic = 1'b1; #10;
        end
    end
endmodule

testbench_vcd/barrel_shifter_testbench.vcd
$date
	Fri May 23 16:31:13 2025
$end
$version
	Icarus Verilog
$end
$timescale
	1s
$end
$scope module barrel_shifter_testbench $end
$var wire 32 ! out [31:0] $end
$var reg 1 " arithmetic $end
$var reg 1 # dir $end
$var reg 5 $ how_many [4:0] $end
$var reg 32 % in [31:0] $end
$scope module dut $end
$var wire 1 " arithmetic $end
$var wire 1 # dir $end
$var wire 5 & how_many [4:0] $end
$var wire 32 ' in [31:0] $end
$var reg 32 ( out [31:0] $end
$var reg 32 ) s0 [31:0] $end
$var reg 32 * s1 [31:0] $end
$var reg 32 + s2 [31:0] $end
$var reg 32 , s3 [31:0] $end
$upscope $end
$scope begin $ivl_for_loop0 $end
$var integer 32 - i [31:0] $end
$upscope $end
$scope begin $ivl_for_loop1 $end
$var integer 32 . i [31:0] $end
$upscope $end
$upscope $end
$enddefinitions $end
$comment Show the parameter values. $end
$dumpall
$end
#0
$dumpvars
bx .
b0 -
b11111111111111111111111111111111 ,
b11111111111111111111111111111111 +
b11111111111111111111111111111111 *
b11111111111111111111111111111111 )
b11111111111111111111111111111111 (
b11111111111111111111111111111111 '
b0 &
b11111111111111111111111111111111 %
b0 $
0#
0"
b11111111111111111111111111111111 !
$end
#10
b11111111111111111111111111111110 !
b11111111111111111111111111111110 (
b11111111111111111111111111111110 ,
b11111111111111111111111111111110 +
b11111111111111111111111111111110 *
b11111111111111111111111111111110 )
b1 $
b1 &
b1 -
#20
b11111111111111111111111111111100 !
b11111111111111111111111111111100 (
b11111111111111111111111111111100 ,
b11111111111111111111111111111100 +
b11111111111111111111111111111100 *
b11111111111111111111111111111111 )
b10 $
b10 &
b10 -
#30
b11111111111111111111111111111000 !
b11111111111111111111111111111000 (
b11111111111111111111111111111000 ,
b11111111111111111111111111111000 +
b11111111111111111111111111111000 *
b11111111111111111111111111111110 )
b11 $
b11 &
b11 -
#40
b11111111111111111111111111110000 !
b11111111111111111111111111110000 (
b11111111111111111111111111110000 ,
b11111111111111111111111111110000 +
b11111111111111111111111111111111 *
b11111111111111111111111111111111 )
b100 $
b100 &
b100 -
#50
b11111111111111111111111111100000 !
b11111111111111111111111111100000 (
b11111111111111111111111111100000 ,
b11111111111111111111111111100000 +
b11111111111111111111111111111110 *
b11111111111111111111111111111110 )
b101 $
b101 &
b101 -
#60
b11111111111111111111111111000000 !
b11111111111111111111111111000000 (
b11111111111111111111111111000000 ,
b11111111111111111111111111000000 +
b11111111111111111111111111111100 *
b11111111111111111111111111111111 )
b110 $
b110 &
b110 -
#70
b11111111111111111111111110000000 !
b11111111111111111111111110000000 (
b11111111111111111111111110000000 ,
b11111111111111111111111110000000 +
b11111111111111111111111111111000 *
b11111111111111111111111111111110 )
b111 $
b111 &
b111 -
#80
b11111111111111111111111100000000 !
b11111111111111111111111100000000 (
b11111111111111111111111100000000 ,
b11111111111111111111111111111111 +
b11111111111111111111111111111111 *
b11111111111111111111111111111111 )
b1000 $
b1000 &
b1000 -
#90
b11111111111111111111111000000000 !
b11111111111111111111111000000000 (
b11111111111111111111111000000000 ,
b11111111111111111111111111111110 +
b11111111111111111111111111111110 *
b11111111111111111111111111111110 )
b1001 $
b1001 &
b1001 -
#100
b11111111111111111111110000000000 !
b11111111111111111111110000000000 (
b11111111111111111111110000000000 ,
b11111111111111111111111111111100 +
b11111111111111111111111111111100 *
b11111111111111111111111111111111 )
b1010 $
b1010 &
b1010 -
#110
b11111111111111111111100000000000 !
b11111111111111111111100000000000 (
b11111111111111111111100000000000 ,
b11111111111111111111111111111000 +
b11111111111111111111111111111000 *
b11111111111111111111111111111110 )
b1011 $
b1011 &
b1011 -
#120
b11111111111111111111000000000000 !
b11111111111111111111000000000000 (
b11111111111111111111000000000000 ,
b11111111111111111111111111110000 +
b11111111111111111111111111111111 *
b11111111111111111111111111111111 )
b1100 $
b1100 &
b1100 -
#130
b11111111111111111110000000000000 !
b11111111111111111110000000000000 (
b11111111111111111110000000000000 ,
b11111111111111111111111111100000 +
b11111111111111111111111111111110 *
b11111111111111111111111111111110 )
b1101 $
b1101 &
b1101 -
#140
b11111111111111111100000000000000 !
b11111111111111111100000000000000 (
b11111111111111111100000000000000 ,
b11111111111111111111111111000000 +
b11111111111111111111111111111100 *
b11111111111111111111111111111111 )
b1110 $
b1110 &
b1110 -
#150
b11111111111111111000000000000000 !
b11111111111111111000000000000000 (
b11111111111111111000000000000000 ,
b11111111111111111111111110000000 +
b11111111111111111111111111111000 *
b11111111111111111111111111111110 )
b1111 $
b1111 &
b1111 -
#160
b11111111111111110000000000000000 !
b11111111111111110000000000000000 (
b11111111111111111111111111111111 ,
b11111111111111111111111111111111 +
b11111111111111111111111111111111 *
b11111111111111111111111111111111 )
b10000 $
b10000 &
b10000 -
#170
b11111111111111100000000000000000 !
b11111111111111100000000000000000 (
b11111111111111111111111111111110 ,
b11111111111111111111111111111110 +
b11111111111111111111111111111110 *
b11111111111111111111111111111110 )
b10001 $
b10001 &
b10001 -
#180
b11111111111111000000000000000000 !
b11111111111111000000000000000000 (
b11111111111111111111111111111100 ,
b11111111111111111111111111111100 +
b11111111111111111111111111111100 *
b11111111111111111111111111111111 )
b10010 $
b10010 &
b10010 -
#190
b11111111111110000000000000000000 !
b11111111111110000000000000000000 (
b11111111111111111111111111111000 ,
b11111111111111111111111111111000 +
b11111111111111111111111111111000 *
b11111111111111111111111111111110 )
b10011 $
b10011 &
b10011 -
#200
b11111111111100000000000000000000 !
b11111111111100000000000000000000 (
b11111111111111111111111111110000 ,
b11111111111111111111111111110000 +
b11111111111111111111111111111111 *
b11111111111111111111111111111111 )
b10100 $
b10100 &
b10100 -
#210
b11111111111000000000000000000000 !
b11111111111000000000000000000000 (
b11111111111111111111111111100000 ,
b11111111111111111111111111100000 +
b11111111111111111111111111111110 *
b11111111111111111111111111111110 )
b10101 $
b10101 &
b10101 -
#220
b11111111110000000000000000000000 !
b11111111110000000000000000000000 (
b11111111111111111111111111000000 ,
b11111111111111111111111111000000 +
b11111111111111111111111111111100 *
b11111111111111111111111111111111 )
b10110 $
b10110 &
b10110 -
#230
b11111111100000000000000000000000 !
b11111111100000000000000000000000 (
b11111111111111111111111110000000 ,
b11111111111111111111111110000000 +
b11111111111111111111111111111000 *
b11111111111111111111111111111110 )
b10111 $
b10111 &
b10111 -
#240
b11111111000000000000000000000000 !
b11111111000000000000000000000000 (
b11111111111111111111111100000000 ,
b11111111111111111111111111111111 +
b11111111111111111111111111111111 *
b11111111111111111111111111111111 )
b11000 $
b11000 &
b11000 -
#250
b11111110000000000000000000000000 !
b11111110000000000000000000000000 (
b11111111111111111111111000000000 ,
b11111111111111111111111111111110 +
b11111111111111111111111111111110 *
b11111111111111111111111111111110 )
b11001 $
b11001 &
b11001 -
#260
b11111100000000000000000000000000 !
b11111100000000000000000000000000 (
b11111111111111111111110000000000 ,
b11111111111111111111111111111100 +
b11111111111111111111111111111100 *
b11111111111111111111111111111111 )
b11010 $
b11010 &
b11010 -
#270
b11111000000000000000000000000000 !
b11111000000000000000000000000000 (
b11111111111111111111100000000000 ,
b11111111111111111111111111111000 +
b11111111111111111111111111111000 *
b11111111111111111111111111111110 )
b11011 $
b11011 &
b11011 -
#280
b11110000000000000000000000000000 !
b11110000000000000000000000000000 (
b11111111111111111111000000000000 ,
b11111111111111111111111111110000 +
b11111111111111111111111111111111 *
b11111111111111111111111111111111 )
b11100 $
b11100 &
b11100 -
#290
b11100000000000000000000000000000 !
b11100000000000000000000000000000 (
b11111111111111111110000000000000 ,
b11111111111111111111111111100000 +
b11111111111111111111111111111110 *
b11111111111111111111111111111110 )
b11101 $
b11101 &
b11101 -
#300
b11000000000000000000000000000000 !
b11000000000000000000000000000000 (
b11111111111111111100000000000000 ,
b11111111111111111111111111000000 +
b11111111111111111111111111111100 *
b11111111111111111111111111111111 )
b11110 $
b11110 &
b11110 -
#310
b10000000000000000000000000000000 !
b10000000000000000000000000000000 (
b11111111111111111000000000000000 ,
b11111111111111111111111110000000 +
b11111111111111111111111111111000 *
b11111111111111111111111111111110 )
b11111 $
b11111 &
b11111 -
#320
b11111111111111111111111111111111 !
b11111111111111111111111111111111 (
b11111111111111111111111111111111 ,
b11111111111111111111111111111111 +
b11111111111111111111111111111111 *
b11111111111111111111111111111111 )
b0 $
b0 &
b100000 -
#330
1#
b0 .
b100001 -
#340
1"
#350
b1111111111111111111111111111111 !
b1111111111111111111111111111111 (
b1111111111111111111111111111111 ,
b1111111111111111111111111111111 +
b1111111111111111111111111111111 *
b1111111111111111111111111111111 )
0"
b1 $
b1 &
b1 .
#360
b11111111111111111111111111111111 !
b11111111111111111111111111111111 (
b11111111111111111111111111111111 ,
b11111111111111111111111111111111 +
b11111111111111111111111111111111 *
b11111111111111111111111111111111 )
1"
#370
b111111111111111111111111111111 !
b111111111111111111111111111111 (
b111111111111111111111111111111 ,
b111111111111111111111111111111 +
b111111111111111111111111111111 *
0"
b10 $
b10 &
b10 .
#380
b11111111111111111111111111111111 !
b11111111111111111111111111111111 (
b11111111111111111111111111111111 ,
b11111111111111111111111111111111 +
b11111111111111111111111111111111 *
1"
#390
b11111111111111111111111111111 !
b11111111111111111111111111111 (
b11111111111111111111111111111 ,
b11111111111111111111111111111 +
b11111111111111111111111111111 *
b1111111111111111111111111111111 )
0"
b11 $
b11 &
b11 .
#400
b11111111111111111111111111111111 !
b11111111111111111111111111111111 (
b11111111111111111111111111111111 ,
b11111111111111111111111111111111 +
b11111111111111111111111111111111 *
b11111111111111111111111111111111 )
1"
#410
b1111111111111111111111111111 !
b1111111111111111111111111111 (
b1111111111111111111111111111 ,
b1111111111111111111111111111 +
0"
b100 $
b100 &
b100 .
#420
b11111111111111111111111111111111 !
b11111111111111111111111111111111 (
b11111111111111111111111111111111 ,
b11111111111111111111111111111111 +
1"
#430
b111111111111111111111111111 !
b111111111111111111111111111 (
b111111111111111111111111111 ,
b111111111111111111111111111 +
b1111111111111111111111111111111 *
b1111111111111111111111111111111 )
0"
b101 $
b101 &
b101 .
#440
b11111111111111111111111111111111 !
b11111111111111111111111111111111 (
b11111111111111111111111111111111 ,
b11111111111111111111111111111111 +
b11111111111111111111111111111111 *
b11111111111111111111111111111111 )
1"
#450
b11111111111111111111111111 !
b11111111111111111111111111 (
b11111111111111111111111111 ,
b11111111111111111111111111 +
b111111111111111111111111111111 *
0"
b110 $
b110 &
b110 .
#460
b11111111111111111111111111111111 !
b11111111111111111111111111111111 (
b11111111111111111111111111111111 ,
b11111111111111111111111111111111 +
b11111111111111111111111111111111 *
1"
#470
b1111111111111111111111111 !
b1111111111111111111111111 (
b1111111111111111111111111 ,
b1111111111111111111111111 +
b11111111111111111111111111111 *
b1111111111111111111111111111111 )
0"
b111 $
b111 &
b111 .
#480
b11111111111111111111111111111111 !
b11111111111111111111111111111111 (
b11111111111111111111111111111111 ,
b11111111111111111111111111111111 +
b11111111111111111111111111111111 *
b11111111111111111111111111111111 )
1"
#490
b111111111111111111111111 !
b111111111111111111111111 (
b111111111111111111111111 ,
0"
b1000 $
b1000 &
b1000 .
#500
b11111111111111111111111111111111 !
b11111111111111111111111111111111 (
b11111111111111111111111111111111 ,
1"
#510
b11111111111111111111111 !
b11111111111111111111111 (
b11111111111111111111111 ,
b1111111111111111111111111111111 +
b1111111111111111111111111111111 *
b1111111111111111111111111111111 )
0"
b1001 $
b1001 &
b1001 .
#520
b11111111111111111111111111111111 !
b11111111111111111111111111111111 (
b11111111111111111111111111111111 ,
b11111111111111111111111111111111 +
b11111111111111111111111111111111 *
b11111111111111111111111111111111 )
1"
#530
b1111111111111111111111 !
b1111111111111111111111 (
b1111111111111111111111 ,
b111111111111111111111111111111 +
b111111111111111111111111111111 *
0"
b1010 $
b1010 &
b1010 .
#540
b11111111111111111111111111111111 !
b11111111111111111111111111111111 (
b11111111111111111111111111111111 ,
b11111111111111111111111111111111 +
b11111111111111111111111111111111 *
1"
#550
b111111111111111111111 !
b111111111111111111111 (
b111111111111111111111 ,
b11111111111111111111111111111 +
b11111111111111111111111111111 *
b1111111111111111111111111111111 )
0"
b1011 $
b1011 &
b1011 .
#560
b11111111111111111111111111111111 !
b11111111111111111111111111111111 (
b11111111111111111111111111111111 ,
b11111111111111111111111111111111 +
b11111111111111111111111111111111 *
b11111111111111111111111111111111 )
1"
#570
b11111111111111111111 !
b11111111111111111111 (
b11111111111111111111 ,
b1111111111111111111111111111 +
0"
b1100 $
b1100 &
b1100 .
#580
b11111111111111111111111111111111 !
b11111111111111111111111111111111 (
b11111111111111111111111111111111 ,
b11111111111111111111111111111111 +
1"
#590
b1111111111111111111 !
b1111111111111111111 (
b1111111111111111111 ,
b111111111111111111111111111 +
b1111111111111111111111111111111 *
b1111111111111111111111111111111 )
0"
b1101 $
b1101 &
b1101 .
#600
b11111111111111111111111111111111 !
b11111111111111111111111111111111 (
b11111111111111111111111111111111 ,
b11111111111111111111111111111111 +
b11111111111111111111111111111111 *
b11111111111111111111111111111111 )
1"
#610
b111111111111111111 !
b111111111111111111 (
b111111111111111111 ,
b11111111111111111111111111 +
b111111111111111111111111111111 *
0"
b1110 $
b1110 &
b1110 .
#620
b11111111111111111111111111111111 !
b11111111111111111111111111111111 (
b11111111111111111111111111111111 ,
b11111111111111111111111111111111 +
b11111111111111111111111111111111 *
1"
#630
b11111111111111111 !
b11111111111111111 (
b11111111111111111 ,
b1111111111111111111111111 +
b11111111111111111111111111111 *
b1111111111111111111111111111111 )
0"
b1111 $
b1111 &
b1111 .
#640
b11111111111111111111111111111111 !
b11111111111111111111111111111111 (
b11111111111111111111111111111111 ,
b11111111111111111111111111111111 +
b11111111111111111111111111111111 *
b11111111111111111111111111111111 )
1"
#650
b1111111111111111 !
b1111111111111111 (
0"
b10000 $
b10000 &
b10000 .
#660
b11111111111111111111111111111111 !
b11111111111111111111111111111111 (
1"
#670
b111111111111111 !
b111111111111111 (
b1111111111111111111111111111111 ,
b1111111111111111111111111111111 +
b1111111111111111111111111111111 *
b1111111111111111111111111111111 )
0"
b10001 $
b10001 &
b10001 .
#680
b11111111111111111111111111111111 !
b11111111111111111111111111111111 (
b11111111111111111111111111111111 ,
b11111111111111111111111111111111 +
b11111111111111111111111111111111 *
b11111111111111111111111111111111 )
1"
#690
b11111111111111 !
b11111111111111 (
b111111111111111111111111111111 ,
b111111111111111111111111111111 +
b111111111111111111111111111111 *
0"
b10010 $
b10010 &
b10010 .
#700
b11111111111111111111111111111111 !
b11111111111111111111111111111111 (
b11111111111111111111111111111111 ,
b11111111111111111111111111111111 +
b11111111111111111111111111111111 *
1"
#710
b1111111111111 !
b1111111111111 (
b11111111111111111111111111111 ,
b11111111111111111111111111111 +
b11111111111111111111111111111 *
b1111111111111111111111111111111 )
0"
b10011 $
b10011 &
b10011 .
#720
b11111111111111111111111111111111 !
b11111111111111111111111111111111 (
b11111111111111111111111111111111 ,
b11111111111111111111111111111111 +
b11111111111111111111111111111111 *
b11111111111111111111111111111111 )
1"
#730
b111111111111 !
b111111111111 (
b1111111111111111111111111111 ,
b1111111111111111111111111111 +
0"
b10100 $
b10100 &
b10100 .
#740
b11111111111111111111111111111111 !
b11111111111111111111111111111111 (
b11111111111111111111111111111111 ,
b11111111111111111111111111111111 +
1"
#750
b11111111111 !
b11111111111 (
b111111111111111111111111111 ,
b111111111111111111111111111 +
b1111111111111111111111111111111 *
b1111111111111111111111111111111 )
0"
b10101 $
b10101 &
b10101 .
#760
b11111111111111111111111111111111 !
b11111111111111111111111111111111 (
b11111111111111111111111111111111 ,
b11111111111111111111111111111111 +
b11111111111111111111111111111111 *
b11111111111111111111111111111111 )
1"
#770
b1111111111 !
b1111111111 (
b11111111111111111111111111 ,
b11111111111111111111111111 +
b111111111111111111111111111111 *
0"
b10110 $
b10110 &
b10110 .
#780
b11111111111111111111111111111111 !
b11111111111111111111111111111111 (
b11111111111111111111111111111111 ,
b11111111111111111111111111111111 +
b11111111111111111111111111111111 *
1"
#790
b111111111 !
b111111111 (
b1111111111111111111111111 ,
b1111111111111111111111111 +
b11111111111111111111111111111 *
b1111111111111111111111111111111 )
0"
b10111 $
b10111 &
b10111 .
#800
b11111111111111111111111111111111 !
b11111111111111111111111111111111 (
b11111111111111111111111111111111 ,
b11111111111111111111111111111111 +
b11111111111111111111111111111111 *
b11111111111111111111111111111111 )
1"
#810
b11111111 !
b11111111 (
b111111111111111111111111 ,
0"
b11000 $
b11000 &
b11000 .
#820
b11111111111111111111111111111111 !
b11111111111111111111111111111111 (
b11111111111111111111111111111111 ,
1"
#830
b1111111 !
b1111111 (
b11111111111111111111111 ,
b1111111111111111111111111111111 +
b1111111111111111111111111111111 *
b1111111111111111111111111111111 )
0"
b11001 $
b11001 &
b11001 .
#840
b11111111111111111111111111111111 !
b11111111111111111111111111111111 (
b11111111111111111111111111111111 ,
b11111111111111111111111111111111 +
b11111111111111111111111111111111 *
b11111111111111111111111111111111 )
1"
#850
b111111 !
b111111 (
b1111111111111111111111 ,
b111111111111111111111111111111 +
b111111111111111111111111111111 *
0"
b11010 $
b11010 &
b11010 .
#860
b11111111111111111111111111111111 !
b11111111111111111111111111111111 (
b11111111111111111111111111111111 ,
b11111111111111111111111111111111 +
b11111111111111111111111111111111 *
1"
#870
b11111 !
b11111 (
b111111111111111111111 ,
b11111111111111111111111111111 +
b11111111111111111111111111111 *
b1111111111111111111111111111111 )
0"
b11011 $
b11011 &
b11011 .
#880
b11111111111111111111111111111111 !
b11111111111111111111111111111111 (
b11111111111111111111111111111111 ,
b11111111111111111111111111111111 +
b11111111111111111111111111111111 *
b11111111111111111111111111111111 )
1"
#890
b1111 !
b1111 (
b11111111111111111111 ,
b1111111111111111111111111111 +
0"
b11100 $
b11100 &
b11100 .
#900
b11111111111111111111111111111111 !
b11111111111111111111111111111111 (
b11111111111111111111111111111111 ,
b11111111111111111111111111111111 +
1"
#910
b111 !
b111 (
b1111111111111111111 ,
b111111111111111111111111111 +
b1111111111111111111111111111111 *
b1111111111111111111111111111111 )
0"
b11101 $
b11101 &
b11101 .
#920
b11111111111111111111111111111111 !
b11111111111111111111111111111111 (
b11111111111111111111111111111111 ,
b11111111111111111111111111111111 +
b11111111111111111111111111111111 *
b11111111111111111111111111111111 )
1"
#930
b11 !
b11 (
b111111111111111111 ,
b11111111111111111111111111 +
b111111111111111111111111111111 *
0"
b11110 $
b11110 &
b11110 .
#940
b11111111111111111111111111111111 !
b11111111111111111111111111111111 (
b11111111111111111111111111111111 ,
b11111111111111111111111111111111 +
b11111111111111111111111111111111 *
1"
#950
b1 !
b1 (
b11111111111111111 ,
b1111111111111111111111111 +
b11111111111111111111111111111 *
b1111111111111111111111111111111 )
0"
b11111 $
b11111 &
b11111 .
#960
b11111111111111111111111111111111 !
b11111111111111111111111111111111 (
b11111111111111111111111111111111 ,
b11111111111111111111111111111111 +
b11111111111111111111111111111111 *
b11111111111111111111111111111111 )
1"
#970
0"
b0 $
b0 &
b100000 .
#980
1"
#990
b100001 .
